{
  "version": "V7",
  "name": "第七轮公开发布运营版最终报告",
  "status": "complete-structure",
  "createdAt": "2026-05-23T11:32:40Z",
  "completedStages": 4,
  "completedBatches": 16,
  "productionLive": false,
  "releaseReady": false,
  "cleanProductionReady": false,
  "checks": {
    "stage01": "passed",
    "stage02": "passed",
    "stage03": "passed",
    "stage04": "passed",
    "checkJson": "passed",
    "checkRepo": "passed",
    "checkV7ReleaseAll": "passed",
    "checkV7ReleasePrivacyBoundary": "passed",
    "lint": "passed",
    "typecheck": "passed",
    "auditReport": "passed-total-2-moderate-2-high-0-critical-0",
    "build": "timeout-after-turbopack-compile-writing-to-disk-current-container"
  },
  "buildNotes": [
    "npm run build completed validate:world, check:public, build:public-json and reached Next Turbopack optimized production build.",
    "Current container timed out after writing build output / during page data or trace collection.",
    "Do not mark clean production-ready until a full build exits 0 in target environment."
  ],
  "nextVersion": "V8 真实生产发布与运维闭环"
}
